analyzefit/__init__.py
analyzefit/analyze.py
analyzefit/manipulate.py
analyzefit/plotting.py
analyzefit-0.3.8.dist-info/DESCRIPTION.rst
analyzefit-0.3.8.dist-info/METADATA
analyzefit-0.3.8.dist-info/RECORD
analyzefit-0.3.8.dist-info/WHEEL
analyzefit-0.3.8.dist-info/metadata.json
analyzefit-0.3.8.dist-info/top_level.txt
