Metadata-Version: 2.0
Name: analyzefit
Version: 0.3.8
Summary: Performs analysis of the fit of a model.
Home-page: https://github.com/wsmorgan/analyzefit
Author: Wiley S Morgan
Author-email: wsmorgan@gmail.com
License: MIT
Platform: UNKNOWN
Classifier: Development Status :: 2 - Pre-Alpha
Classifier: Intended Audience :: Science/Research
Classifier: Natural Language :: English
Classifier: Operating System :: MacOS
Classifier: Programming Language :: Python
Classifier: Programming Language :: Python :: 2
Classifier: Programming Language :: Python :: 2.7
Classifier: Programming Language :: Python :: 3
Classifier: Programming Language :: Python :: 3.5
Requires-Dist: bokeh
Requires-Dist: matplotlib
Requires-Dist: numpy
Requires-Dist: scipy
Requires-Dist: sklearn
